databox/__init__.py
databox/_nbdev.py
databox/core.py
databox/utils.py
lazybox/__init__.py
lazybox/_nbdev.py
lazybox/all.py
lazybox/box.py
lazybox/core.py
lazybox/utils.py
lazybox-0.0.2.5.dist-info/LICENSE
lazybox-0.0.2.5.dist-info/METADATA
lazybox-0.0.2.5.dist-info/WHEEL
lazybox-0.0.2.5.dist-info/entry_points.txt
lazybox-0.0.2.5.dist-info/top_level.txt
lazybox-0.0.2.5.dist-info/RECORD
