Metadata-Version: 2.1
Name: lazybox
Version: 0.0.2.5
Summary: A description of your project
Home-page: https://github.com/limiteinductive/Databox/tree/main/
Author: Benjamin Trom
Author-email: benjamintrom@gmail.com
License: MIT License
Keywords: some keywords
Platform: UNKNOWN
Classifier: Development Status :: 3 - Alpha
Classifier: Intended Audience :: Developers
Classifier: Natural Language :: English
Classifier: Programming Language :: Python :: 3.6
Classifier: Programming Language :: Python :: 3.7
Classifier: Programming Language :: Python :: 3.8
Classifier: License :: OSI Approved :: MIT License
Requires-Python: >=3.6
License-File: LICENSE
Requires-Dist: pip
Requires-Dist: packaging
Requires-Dist: fastai
Requires-Dist: plum-dispatch
Requires-Dist: python-Levenshtein
Requires-Dist: fuzzywuzzy
Provides-Extra: dev
